[
    {
        "id": "S101",
        "sname": "Ambulance Service",
        "img": "imges/services/ambu.jpg"
    },
    {
        "id": "S102",
        "sname": "Operation Theater",
        "img": "imges/services/badperation.jpg"
    },
    {
        "id": "S103",
        "sname": "ICU Bed",
        "img": "imges/services/badicu.jpg"
    },
    {
        "id": "S104",
        "sname": "Blood Test",
        "img": "imges/services/blood.jpg"
    },
    {
        "id": "S105",
        "sname": "Brain Scan",
        "img": "imges/services/brain.jpg"
    },
    {
        "id": "S106",
        "sname": "Dental Treatment",
        "img": "imges/services/dental.jpg"
    },
    {
        "id": "S107",
        "sname": "DNA Test",
        "img": "imges/services/dna.jpg"
    },
    {
        "id": "S108",
        "sname": "EYE Treatment",
        "img": "imges/services/eye.jpg"
    },
    {
        "id": "S109",
        "sname": "Ear Treatment",
        "img": "imges/services/hear.jpg"
    },
    {
        "id": "S110",
        "sname": "Indoor Treatment",
        "img": "imges/services/indoor.jpg"
    },
    {
        "id": "S111",
        "sname": "Medicine Service",
        "img": "imges/services/medicine.jpg"
    },
    {
        "id": "S112",
        "sname": "MRI Test",
        "img": "imges/services/mri.jpg"
    },
    {
        "id": "S113",
        "sname": "Nose Treatment",
        "img": "imges/services/nose.jpg"
    },
    {
        "id": "S114",
        "sname": "Orthopadic",
        "img": "imges/services/orthopadic.jpg"
    },
    {
        "id": "S115",
        "sname": "Outdoor Treatment",
        "img": "imges/services/outdoor.jpg"
    },
    {
        "id": "S116",
        "sname": "Xray",
        "img": "imges/services/scaning.jpg"
    },
    {
        "id": "S117",
        "sname": "Skin Treatment",
        "img": "imges/services/skin.jpg"
    },
    {
        "id": "S118",
        "sname": "Ultrasonogram",
        "img": "imges/services/ultra.jpg"
    },
    {
        "id": "S119",
        "sname": "Report Delivery",
        "img": "imges/services/xray.jpg"
    },
    {
        "id": "S120",
        "sname": "ICU Ventilator",
        "img": "imges/services/vantilator.jpg"
    },
    {
        "id": "S121",
        "sname": "Hospital Bed",
        "img": "imges/services/cabin.jpg"
    }
]